{
    "key": "group_5685bfb5be8d4",
    "title": "Info",
    "fields": [
        {
            "key": "field_5685bfbc48fe2",
            "label": "Introduction Text",
            "name": "info_text",
            "type": "wysiwyg",
            "instructions": "",
            "required": 0,
            "conditional_logic": 0,
            "wrapper": {
                "width": "",
                "class": "",
                "id": ""
            },
            "default_value": "",
            "tabs": "all",
            "toolbar": "full",
            "media_upload": 1
        },
        {
            "key": "field_569536f46881f",
            "label": "Bio Image",
            "name": "info_image",
            "type": "image",
            "instructions": "",
            "required": 0,
            "conditional_logic": 0,
            "wrapper": {
                "width": "",
                "class": "",
                "id": ""
            },
            "return_format": "array",
            "preview_size": "thumbnail",
            "library": "all",
            "min_width": "",
            "min_height": "",
            "min_size": "",
            "max_width": "",
            "max_height": "",
            "max_size": "",
            "mime_types": ""
        },
        {
            "key": "field_5685c20b48fe3",
            "label": "Contact",
            "name": "info_contact",
            "type": "repeater",
            "instructions": "",
            "required": 0,
            "conditional_logic": 0,
            "wrapper": {
                "width": "",
                "class": "",
                "id": ""
            },
            "collapsed": "",
            "min": "",
            "max": "",
            "layout": "table",
            "button_label": "Add Contact",
            "sub_fields": [
                {
                    "key": "field_5685c2fc48fe4",
                    "label": "Contact Name",
                    "name": "info_contact_name",
                    "type": "text",
                    "instructions": "",
                    "required": 0,
                    "conditional_logic": 0,
                    "wrapper": {
                        "width": "",
                        "class": "",
                        "id": ""
                    },
                    "default_value": "",
                    "placeholder": "",
                    "prepend": "",
                    "append": "",
                    "maxlength": "",
                    "readonly": 0,
                    "disabled": 0
                },
                {
                    "key": "field_5685c31948fe5",
                    "label": "Contact Address",
                    "name": "info_contact_address",
                    "type": "text",
                    "instructions": "",
                    "required": 0,
                    "conditional_logic": 0,
                    "wrapper": {
                        "width": "",
                        "class": "",
                        "id": ""
                    },
                    "default_value": "",
                    "placeholder": "",
                    "prepend": "",
                    "append": "",
                    "maxlength": "",
                    "readonly": 0,
                    "disabled": 0
                }
            ]
        },
        {
            "key": "field_5685c33b48fe6",
            "label": "Colophon",
            "name": "info_colophon",
            "type": "repeater",
            "instructions": "",
            "required": 0,
            "conditional_logic": 0,
            "wrapper": {
                "width": "",
                "class": "",
                "id": ""
            },
            "collapsed": "",
            "min": "",
            "max": "",
            "layout": "table",
            "button_label": "Add Colophon Row",
            "sub_fields": [
                {
                    "key": "field_5685c37248fe7",
                    "label": "Colophon Title",
                    "name": "info_colophon_title",
                    "type": "text",
                    "instructions": "",
                    "required": 0,
                    "conditional_logic": 0,
                    "wrapper": {
                        "width": "",
                        "class": "",
                        "id": ""
                    },
                    "default_value": "",
                    "placeholder": "",
                    "prepend": "",
                    "append": "",
                    "maxlength": "",
                    "readonly": 0,
                    "disabled": 0
                },
                {
                    "key": "field_5685c38348fe8",
                    "label": "Colophon Name",
                    "name": "info_colophon_name",
                    "type": "text",
                    "instructions": "",
                    "required": 0,
                    "conditional_logic": 0,
                    "wrapper": {
                        "width": "",
                        "class": "",
                        "id": ""
                    },
                    "default_value": "",
                    "placeholder": "",
                    "prepend": "",
                    "append": "",
                    "maxlength": "",
                    "readonly": 0,
                    "disabled": 0
                }
            ]
        },
        {
            "key": "field_5685c3a148fe9",
            "label": "Stockists",
            "name": "info_stockists",
            "type": "repeater",
            "instructions": "",
            "required": 0,
            "conditional_logic": 0,
            "wrapper": {
                "width": "",
                "class": "",
                "id": ""
            },
            "collapsed": "",
            "min": "",
            "max": "",
            "layout": "table",
            "button_label": "Add Country",
            "sub_fields": [
                {
                    "key": "field_5685c41c48fea",
                    "label": "Country",
                    "name": "info_stockists_country",
                    "type": "text",
                    "instructions": "",
                    "required": 0,
                    "conditional_logic": 0,
                    "wrapper": {
                        "width": "",
                        "class": "",
                        "id": ""
                    },
                    "default_value": "",
                    "placeholder": "",
                    "prepend": "",
                    "append": "",
                    "maxlength": "",
                    "readonly": 0,
                    "disabled": 0
                },
                {
                    "key": "field_5685c43648feb",
                    "label": "Stockists",
                    "name": "info_stockists_names",
                    "type": "repeater",
                    "instructions": "",
                    "required": 0,
                    "conditional_logic": 0,
                    "wrapper": {
                        "width": "",
                        "class": "",
                        "id": ""
                    },
                    "collapsed": "",
                    "min": "",
                    "max": "",
                    "layout": "table",
                    "button_label": "Add Stockist",
                    "sub_fields": [
                        {
                            "key": "field_5685c45248fec",
                            "label": "Stockist Name",
                            "name": "info_stockists_name",
                            "type": "text",
                            "instructions": "",
                            "required": 0,
                            "conditional_logic": 0,
                            "wrapper": {
                                "width": "",
                                "class": "",
                                "id": ""
                            },
                            "default_value": "",
                            "placeholder": "",
                            "prepend": "",
                            "append": "",
                            "maxlength": "",
                            "readonly": 0,
                            "disabled": 0
                        }
                    ]
                }
            ]
        }
    ],
    "location": [
        [
            {
                "param": "post",
                "operator": "==",
                "value": "119"
            }
        ]
    ],
    "menu_order": 0,
    "position": "normal",
    "style": "default",
    "label_placement": "top",
    "instruction_placement": "label",
    "hide_on_screen": [
        "permalink",
        "the_content",
        "excerpt",
        "custom_fields",
        "discussion",
        "comments",
        "revisions",
        "slug",
        "author",
        "format",
        "page_attributes",
        "featured_image",
        "categories",
        "tags",
        "send-trackbacks"
    ],
    "active": 1,
    "description": "",
    "modified": 1473010848
}